{"components": [{"bom-ref": "BomRef.946084528250272.9720416722856347", "name": "altair", "type": "library", "version": "6.2.1"}, {"bom-ref": "BomRef.2812577946624968.7679365664533608", "name": "annotated-doc", "type": "library", "version": "0.0.4"}, {"bom-ref": "BomRef.3094425215101618.5434689842367982", "name": "annotated-types", "type": "library", "version": "0.7.0"}, {"bom-ref": "BomRef.9555010294142502.7393913907566925", "name": "anyio", "type": "library", "version": "4.14.0"}, {"bom-ref": "BomRef.7113328605007135.9556352741617771", "name": "ast-serialize", "type": "library", "version": "0.5.0"}, {"bom-ref": "BomRef.7322151312063863.15630250457850647", "name": "attrs", "type": "library", "version": "26.1.0"}, {"bom-ref": "BomRef.5856925151724669.6049718155763594", "name": "bandit", "type": "library", "version": "1.9.4"}, {"bom-ref": "BomRef.2194256878145363.032082925196114886", "name": "blinker", "type": "library", "version": "1.9.0"}, {"bom-ref": "BomRef.19507243947637143.4549153488222851", "name": "boolean-py", "type": "library", "version": "5.0"}, {"bom-ref": "BomRef.3577466629007551.408869754348533", "name": "cachecontrol", "type": "library", "version": "0.14.4"}, {"bom-ref": "BomRef.5000453200510426.5827829827064653", "name": "cachetools", "type": "library", "version": "7.1.4"}, {"bom-ref": "BomRef.8416444172671227.926183573150287", "name": "certifi", "type": "library", "version": "2026.6.17"}, {"bom-ref": "BomRef.5390306540661807.596281016534274", "name": "cfgv", "type": "library", "version": "3.5.0"}, {"bom-ref": "BomRef.9500375501838764.26196138531617497", "name": "charset-normalizer", "type": "library", "version": "3.4.7"}, {"bom-ref": "BomRef.4490053617363815.07786332429719123", "name": "click", "type": "library", "version": "8.4.1"}, {"bom-ref": "BomRef.5736877967868615.4299848312050931", "name": "coverage", "type": "library", "version": "7.14.3"}, {"bom-ref": "BomRef.7106727829954812.17197698957078567", "name": "cuda-bindings", "type": "library", "version": "13.3.1"}, {"bom-ref": "BomRef.8790773462058938.20104419892381864", "name": "cuda-pathfinder", "type": "library", "version": "1.5.5"}, {"bom-ref": "BomRef.0467741209241852.5904127443445574", "name": "cuda-toolkit", "type": "library", "version": "13.0.2"}, {"bom-ref": "BomRef.6831432901355264.41338237399294275", "name": "cyclonedx-python-lib", "type": "library", "version": "11.11.0"}, {"bom-ref": "BomRef.5442303678567701.9229315377162145", "name": "defusedxml", "type": "library", "version": "0.7.1"}, {"bom-ref": "BomRef.906389014583216.0926475639659724", "name": "detect-secrets", "type": "library", "version": "1.5.0"}, {"bom-ref": "BomRef.40588853066889286.2196320701248674", "name": "distlib", "type": "library", "version": "0.4.3"}, {"bom-ref": "BomRef.10010036407220202.3176398652079996", "name": "filelock", "type": "library", "version": "3.29.4"}, {"bom-ref": "BomRef.46789964654511607.7590578919149885", "name": "fsspec", "type": "library", "version": "2026.6.0"}, {"bom-ref": "BomRef.43501854079968527.2200993581936752", "name": "gitdb", "type": "library", "version": "4.0.12"}, {"bom-ref": "BomRef.42723052080988533.8074695739967055", "name": "gitpython", "type": "library", "version": "3.1.50"}, {"bom-ref": "BomRef.19356304957076864.6892496908932753", "name": "grpcio", "type": "library", "version": "1.81.1"}, {"bom-ref": "BomRef.8211668301153788.13416718098016134", "name": "h11", "type": "library", "version": "0.16.0"}, {"bom-ref": "BomRef.9091347307262968.9298046928453801", "name": "h2", "type": "library", "version": "4.3.0"}, {"bom-ref": "BomRef.8904358925853593.4697157957256769", "name": "hf-xet", "type": "library", "version": "1.5.1"}, {"bom-ref": "BomRef.5077884554234672.7719147135359736", "name": "hpack", "type": "library", "version": "4.1.0"}, {"bom-ref": "BomRef.19221701723697904.13330330632253728", "name": "httpcore", "type": "library", "version": "1.0.9"}, {"bom-ref": "BomRef.6050390532956018.9138368382326683", "name": "httptools", "type": "library", "version": "0.8.0"}, {"bom-ref": "BomRef.5375715930045538.5168548768001656", "name": "httpx", "type": "library", "version": "0.28.1"}, {"bom-ref": "BomRef.4890062176926824.5979556764193446", "name": "huggingface-hub", "type": "library", "version": "1.20.1"}, {"bom-ref": "BomRef.16646774436078726.3771731486354928", "name": "hyperframe", "type": "library", "version": "6.1.0"}, {"bom-ref": "BomRef.3622169917861471.05216509823760407", "name": "identify", "type": "library", "version": "2.6.19"}, {"bom-ref": "BomRef.257960698401726.3510070420878709", "name": "idna", "type": "library", "version": "3.18"}, {"bom-ref": "BomRef.6580570921014888.9951550796619147", "name": "iniconfig", "type": "library", "version": "2.3.0"}, {"bom-ref": "BomRef.020924648108319177.6086603608465073", "name": "itsdangerous", "type": "library", "version": "2.2.0"}, {"bom-ref": "BomRef.9762755608226122.338981861713919", "name": "jinja2", "type": "library", "version": "3.1.6"}, {"bom-ref": "BomRef.06363677939175649.6038470241987495", "name": "joblib", "type": "library", "version": "1.5.3"}, {"bom-ref": "BomRef.6992461754526389.7510895063046414", "name": "jsonschema", "type": "library", "version": "4.26.0"}, {"bom-ref": "BomRef.18264250726691333.3768053849296773", "name": "jsonschema-specifications", "type": "library", "version": "2025.9.1"}, {"bom-ref": "BomRef.028391933989983187.17415286448544787", "name": "librt", "type": "library", "version": "0.11.0"}, {"bom-ref": "BomRef.1380070939632091.5022914886246235", "name": "license-expression", "type": "library", "version": "30.4.4"}, {"bom-ref": "BomRef.9756996271792152.08987728010393159", "name": "markdown-it-py", "type": "library", "version": "4.2.0"}, {"bom-ref": "BomRef.8841994252550259.6093844834991451", "name": "markupsafe", "type": "library", "version": "3.0.3"}, {"bom-ref": "BomRef.13981863881012346.8920615447872026", "name": "mdurl", "type": "library", "version": "0.1.2"}, {"bom-ref": "BomRef.01525542847167738.4069654891748058", "name": "mpmath", "type": "library", "version": "1.3.0"}, {"bom-ref": "BomRef.0832850791602674.5863997202996957", "name": "msgpack", "type": "library", "version": "1.2.1"}, {"bom-ref": "BomRef.3564891586836494.886360792727006", "name": "mypy", "type": "library", "version": "2.1.0"}, {"bom-ref": "BomRef.306393522984691.5228945462732087", "name": "mypy-extensions", "type": "library", "version": "1.1.0"}, {"bom-ref": "BomRef.8383120734283115.7280510717171598", "name": "narwhals", "type": "library", "version": "2.22.1"}, {"bom-ref": "BomRef.21016176040747514.9801665569851543", "name": "networkx", "type": "library", "version": "3.6.1"}, {"bom-ref": "BomRef.6348965237280261.1920778391111716", "name": "nodeenv", "type": "library", "version": "1.10.0"}, {"bom-ref": "BomRef.4041591570645612.16420656896092012", "name": "numpy", "type": "library", "version": "2.5.0"}, {"bom-ref": "BomRef.4016771006675379.8004849409471532", "name": "nvidia-cublas", "type": "library", "version": "13.1.1.3"}, {"bom-ref": "BomRef.19601846057089478.5081472927452891", "name": "nvidia-cuda-cupti", "type": "library", "version": "13.0.85"}, {"bom-ref": "BomRef.09532012014585212.29412110741434294", "name": "nvidia-cuda-nvrtc", "type": "library", "version": "13.0.88"}, {"bom-ref": "BomRef.33441548046007796.41123957256873", "name": "nvidia-cuda-runtime", "type": "library", "version": "13.0.96"}, {"bom-ref": "BomRef.6918129463455259.9468169449604915", "name": "nvidia-cudnn-cu13", "type": "library", "version": "9.20.0.48"}, {"bom-ref": "BomRef.9653513611439518.23564826610827172", "name": "nvidia-cufft", "type": "library", "version": "12.0.0.61"}, {"bom-ref": "BomRef.2554085207305885.34442501586498764", "name": "nvidia-cufile", "type": "library", "version": "1.15.1.6"}, {"bom-ref": "BomRef.25471583924079955.6831952332470584", "name": "nvidia-curand", "type": "library", "version": "10.4.0.35"}, {"bom-ref": "BomRef.5339405420817237.4795687521060402", "name": "nvidia-cusolver", "type": "library", "version": "12.0.4.66"}, {"bom-ref": "BomRef.341329843453396.3469732367697903", "name": "nvidia-cusparse", "type": "library", "version": "12.6.3.3"}, {"bom-ref": "BomRef.4089735172128258.28251335788193066", "name": "nvidia-cusparselt-cu13", "type": "library", "version": "0.8.1"}, {"bom-ref": "BomRef.5537772586595694.5913087468910234", "name": "nvidia-nccl-cu13", "type": "library", "version": "2.29.7"}, {"bom-ref": "BomRef.10990069461693774.0012012006842544443", "name": "nvidia-nvjitlink", "type": "library", "version": "13.0.88"}, {"bom-ref": "BomRef.6743767678528101.7269812227437155", "name": "nvidia-nvshmem-cu13", "type": "library", "version": "3.4.5"}, {"bom-ref": "BomRef.3347587264371039.932865553355352", "name": "nvidia-nvtx", "type": "library", "version": "13.0.85"}, {"bom-ref": "BomRef.4359147433391346.984866247331607", "name": "packageurl-python", "type": "library", "version": "0.17.6"}, {"bom-ref": "BomRef.613167293534557.6816576098647429", "name": "packaging", "type": "library", "version": "26.2"}, {"bom-ref": "BomRef.8469895377413493.4091653914070247", "name": "pandas", "type": "library", "version": "3.0.3"}, {"bom-ref": "BomRef.9005669283075488.4531662567715601", "name": "pathspec", "type": "library", "version": "1.1.1"}, {"bom-ref": "BomRef.9310965691081283.6732072686612556", "name": "pillow", "type": "library", "version": "12.2.0"}, {"bom-ref": "BomRef.3442489204650717.2965494017452408", "name": "pip", "type": "library", "version": "26.1.2"}, {"bom-ref": "BomRef.6311435328645971.8032587635184514", "name": "pip-api", "type": "library", "version": "0.0.34"}, {"bom-ref": "BomRef.19184968580433304.9255150120750851", "name": "pip-audit", "type": "library", "version": "2.10.1"}, {"bom-ref": "BomRef.47489961453505203.31406701785327906", "name": "pip-requirements-parser", "type": "library", "version": "32.0.1"}, {"bom-ref": "BomRef.05925434364522275.7665811869041861", "name": "platformdirs", "type": "library", "version": "4.10.0"}, {"bom-ref": "BomRef.7829826871814832.7608884104862831", "name": "pluggy", "type": "library", "version": "1.6.0"}, {"bom-ref": "BomRef.6452545806228636.12287746458786353", "name": "portalocker", "type": "library", "version": "3.2.0"}, {"bom-ref": "BomRef.7232729525902583.686408138680244", "name": "pre-commit", "type": "library", "version": "4.6.0"}, {"bom-ref": "BomRef.30888077906339084.4336581479476056", "name": "protobuf", "type": "library", "version": "7.35.1"}, {"bom-ref": "BomRef.2652614829671902.08845314832094009", "name": "py-serializable", "type": "library", "version": "2.1.0"}, {"bom-ref": "BomRef.9030710234415519.3898658692188427", "name": "pyarrow", "type": "library", "version": "24.0.0"}, {"bom-ref": "BomRef.9323938784552889.033040838742968814", "name": "pydantic", "type": "library", "version": "2.13.4"}, {"bom-ref": "BomRef.45524723858811456.08474575710100518", "name": "pydantic-core", "type": "library", "version": "2.46.4"}, {"bom-ref": "BomRef.4151241764811937.7988838222516954", "name": "pydeck", "type": "library", "version": "0.9.2"}, {"bom-ref": "BomRef.8694090372348136.778617654467549", "name": "pygments", "type": "library", "version": "2.20.0"}, {"bom-ref": "BomRef.9881861706008136.6600129289201654", "name": "pyparsing", "type": "library", "version": "3.3.2"}, {"bom-ref": "BomRef.7791144226107911.1059632306272088", "name": "pytest", "type": "library", "version": "9.1.1"}, {"bom-ref": "BomRef.3841303394889607.03536218045289541", "name": "pytest-cov", "type": "library", "version": "7.1.0"}, {"bom-ref": "BomRef.6417637412689788.6127480579264394", "name": "python-dateutil", "type": "library", "version": "2.9.0.post0"}, {"bom-ref": "BomRef.5777255719114274.17584999750701014", "name": "python-discovery", "type": "library", "version": "1.4.2"}, {"bom-ref": "BomRef.34479402023616823.9785701087806826", "name": "python-multipart", "type": "library", "version": "0.0.32"}, {"bom-ref": "BomRef.7543066008924597.644470797767721", "name": "pyyaml", "type": "library", "version": "6.0.3"}, {"bom-ref": "BomRef.1939533428713378.6474139048630413", "name": "qdrant-client", "type": "library", "version": "1.18.0"}, {"bom-ref": "BomRef.11171272100500274.7894557412007827", "name": "referencing", "type": "library", "version": "0.37.0"}, {"bom-ref": "BomRef.9736467397543925.4045819274572784", "name": "regex", "type": "library", "version": "2026.5.9"}, {"bom-ref": "BomRef.6942021892584074.5748092195724882", "name": "requests", "type": "library", "version": "2.34.2"}, {"bom-ref": "BomRef.48187889075657964.19901674660060975", "name": "rich", "type": "library", "version": "15.0.0"}, {"bom-ref": "BomRef.813066367868474.8563078671542272", "name": "rpds-py", "type": "library", "version": "2026.5.1"}, {"bom-ref": "BomRef.03518225304653444.06041066765113379", "name": "ruff", "type": "library", "version": "0.15.18"}, {"bom-ref": "BomRef.8982286851756128.6213442290605593", "name": "safetensors", "type": "library", "version": "0.8.0"}, {"bom-ref": "BomRef.7134151564880283.38609432472679805", "name": "scikit-learn", "type": "library", "version": "1.9.0"}, {"bom-ref": "BomRef.6130618927771291.44544268082390626", "name": "scipy", "type": "library", "version": "1.18.0"}, {"bom-ref": "BomRef.5720960598545737.7655679882825308", "name": "sentence-transformers", "type": "library", "version": "5.6.0"}, {"bom-ref": "BomRef.10019714764736998.6378379180988782", "name": "setuptools", "type": "library", "version": "81.0.0"}, {"bom-ref": "BomRef.6788307381703613.05486168545949355", "name": "shellingham", "type": "library", "version": "1.5.4"}, {"bom-ref": "BomRef.3922336019633368.4718037210338131", "name": "six", "type": "library", "version": "1.17.0"}, {"bom-ref": "BomRef.7377623823272478.45407423468931296", "name": "smmap", "type": "library", "version": "5.0.3"}, {"bom-ref": "BomRef.10636657497428315.14017516265654528", "name": "sortedcontainers", "type": "library", "version": "2.4.0"}, {"bom-ref": "BomRef.02491847202783759.8500921202260611", "name": "starlette", "type": "library", "version": "1.3.1"}, {"bom-ref": "BomRef.484738844689798.43019252066703295", "name": "stevedore", "type": "library", "version": "5.8.0"}, {"bom-ref": "BomRef.08065291488709037.6108186870844865", "name": "streamlit", "type": "library", "version": "1.58.0"}, {"bom-ref": "BomRef.37636271634664964.1906970421646227", "name": "sympy", "type": "library", "version": "1.14.0"}, {"bom-ref": "BomRef.4407595010060289.4773557775298145", "name": "tenacity", "type": "library", "version": "9.1.4"}, {"bom-ref": "BomRef.07218538021765297.8484015530659847", "name": "threadpoolctl", "type": "library", "version": "3.6.0"}, {"bom-ref": "BomRef.15922550925104262.9927410057966216", "name": "tokenizers", "type": "library", "version": "0.22.2"}, {"bom-ref": "BomRef.8366084590289321.1114078513054112", "name": "toml", "type": "library", "version": "0.10.2"}, {"bom-ref": "BomRef.349560671751335.20193604568927304", "name": "tomli", "type": "library", "version": "2.4.1"}, {"bom-ref": "BomRef.4521618852668089.7174305612753057", "name": "tomli-w", "type": "library", "version": "1.2.0"}, {"bom-ref": "BomRef.7428805630182203.4877805608901593", "name": "torch", "type": "library", "version": "2.12.1"}, {"bom-ref": "BomRef.20626595928813474.7574599005844003", "name": "tqdm", "type": "library", "version": "4.68.3"}, {"bom-ref": "BomRef.9935845075961814.6691869783231301", "name": "transformers", "type": "library", "version": "5.12.1"}, {"bom-ref": "BomRef.554426480310789.01978462700572403", "name": "triton", "type": "library", "version": "3.7.1"}, {"bom-ref": "BomRef.6344301008695711.3340836839382778", "name": "typer", "type": "library", "version": "0.25.1"}, {"bom-ref": "BomRef.9540461553556236.8523954278642786", "name": "typing-extensions", "type": "library", "version": "4.15.0"}, {"bom-ref": "BomRef.02898435239236552.5132771719521404", "name": "typing-inspection", "type": "library", "version": "0.4.2"}, {"bom-ref": "BomRef.5331467007698392.2126073949114068", "name": "urllib3", "type": "library", "version": "2.7.0"}, {"bom-ref": "BomRef.5950705482040816.10831939700154936", "name": "uvicorn", "type": "library", "version": "0.49.0"}, {"bom-ref": "BomRef.609075122463181.8198106997226959", "name": "virtualenv", "type": "library", "version": "21.5.1"}, {"bom-ref": "BomRef.6669977398024305.4723217036713029", "name": "watchdog", "type": "library", "version": "6.0.0"}, {"bom-ref": "BomRef.14757184687490577.5506383763022895", "name": "websockets", "type": "library", "version": "16.0"}], "dependencies": [{"ref": "BomRef.01525542847167738.4069654891748058"}, {"ref": "BomRef.020924648108319177.6086603608465073"}, {"ref": "BomRef.02491847202783759.8500921202260611"}, {"ref": "BomRef.028391933989983187.17415286448544787"}, {"ref": "BomRef.02898435239236552.5132771719521404"}, {"ref": "BomRef.03518225304653444.06041066765113379"}, {"ref": "BomRef.0467741209241852.5904127443445574"}, {"ref": "BomRef.05925434364522275.7665811869041861"}, {"ref": "BomRef.06363677939175649.6038470241987495"}, {"ref": "BomRef.07218538021765297.8484015530659847"}, {"ref": "BomRef.08065291488709037.6108186870844865"}, {"ref": "BomRef.0832850791602674.5863997202996957"}, {"ref": "BomRef.09532012014585212.29412110741434294"}, {"ref": "BomRef.10010036407220202.3176398652079996"}, {"ref": "BomRef.10019714764736998.6378379180988782"}, {"ref": "BomRef.10636657497428315.14017516265654528"}, {"ref": "BomRef.10990069461693774.0012012006842544443"}, {"ref": "BomRef.11171272100500274.7894557412007827"}, {"ref": "BomRef.1380070939632091.5022914886246235"}, {"ref": "BomRef.13981863881012346.8920615447872026"}, {"ref": "BomRef.14757184687490577.5506383763022895"}, {"ref": "BomRef.15922550925104262.9927410057966216"}, {"ref": "BomRef.16646774436078726.3771731486354928"}, {"ref": "BomRef.18264250726691333.3768053849296773"}, {"ref": "BomRef.19184968580433304.9255150120750851"}, {"ref": "BomRef.19221701723697904.13330330632253728"}, {"ref": "BomRef.19356304957076864.6892496908932753"}, {"ref": "BomRef.1939533428713378.6474139048630413"}, {"ref": "BomRef.19507243947637143.4549153488222851"}, {"ref": "BomRef.19601846057089478.5081472927452891"}, {"ref": "BomRef.20626595928813474.7574599005844003"}, {"ref": "BomRef.21016176040747514.9801665569851543"}, {"ref": "BomRef.2194256878145363.032082925196114886"}, {"ref": "BomRef.25471583924079955.6831952332470584"}, {"ref": "BomRef.2554085207305885.34442501586498764"}, {"ref": "BomRef.257960698401726.3510070420878709"}, {"ref": "BomRef.2652614829671902.08845314832094009"}, {"ref": "BomRef.2812577946624968.7679365664533608"}, {"ref": "BomRef.306393522984691.5228945462732087"}, {"ref": "BomRef.30888077906339084.4336581479476056"}, {"ref": "BomRef.3094425215101618.5434689842367982"}, {"ref": "BomRef.33441548046007796.41123957256873"}, {"ref": "BomRef.3347587264371039.932865553355352"}, {"ref": "BomRef.341329843453396.3469732367697903"}, {"ref": "BomRef.3442489204650717.2965494017452408"}, {"ref": "BomRef.34479402023616823.9785701087806826"}, {"ref": "BomRef.349560671751335.20193604568927304"}, {"ref": "BomRef.3564891586836494.886360792727006"}, {"ref": "BomRef.3577466629007551.408869754348533"}, {"ref": "BomRef.3622169917861471.05216509823760407"}, {"ref": "BomRef.37636271634664964.1906970421646227"}, {"ref": "BomRef.3841303394889607.03536218045289541"}, {"ref": "BomRef.3922336019633368.4718037210338131"}, {"ref": "BomRef.4016771006675379.8004849409471532"}, {"ref": "BomRef.4041591570645612.16420656896092012"}, {"ref": "BomRef.40588853066889286.2196320701248674"}, {"ref": "BomRef.4089735172128258.28251335788193066"}, {"ref": "BomRef.4151241764811937.7988838222516954"}, {"ref": "BomRef.42723052080988533.8074695739967055"}, {"ref": "BomRef.43501854079968527.2200993581936752"}, {"ref": "BomRef.4359147433391346.984866247331607"}, {"ref": "BomRef.4407595010060289.4773557775298145"}, {"ref": "BomRef.4490053617363815.07786332429719123"}, {"ref": "BomRef.4521618852668089.7174305612753057"}, {"ref": "BomRef.45524723858811456.08474575710100518"}, {"ref": "BomRef.46789964654511607.7590578919149885"}, {"ref": "BomRef.47489961453505203.31406701785327906"}, {"ref": "BomRef.48187889075657964.19901674660060975"}, {"ref": "BomRef.484738844689798.43019252066703295"}, {"ref": "BomRef.4890062176926824.5979556764193446"}, {"ref": "BomRef.5000453200510426.5827829827064653"}, {"ref": "BomRef.5077884554234672.7719147135359736"}, {"ref": "BomRef.5331467007698392.2126073949114068"}, {"ref": "BomRef.5339405420817237.4795687521060402"}, {"ref": "BomRef.5375715930045538.5168548768001656"}, {"ref": "BomRef.5390306540661807.596281016534274"}, {"ref": "BomRef.5442303678567701.9229315377162145"}, {"ref": "BomRef.5537772586595694.5913087468910234"}, {"ref": "BomRef.554426480310789.01978462700572403"}, {"ref": "BomRef.5720960598545737.7655679882825308"}, {"ref": "BomRef.5736877967868615.4299848312050931"}, {"ref": "BomRef.5777255719114274.17584999750701014"}, {"ref": "BomRef.5856925151724669.6049718155763594"}, {"ref": "BomRef.5950705482040816.10831939700154936"}, {"ref": "BomRef.6050390532956018.9138368382326683"}, {"ref": "BomRef.609075122463181.8198106997226959"}, {"ref": "BomRef.6130618927771291.44544268082390626"}, {"ref": "BomRef.613167293534557.6816576098647429"}, {"ref": "BomRef.6311435328645971.8032587635184514"}, {"ref": "BomRef.6344301008695711.3340836839382778"}, {"ref": "BomRef.6348965237280261.1920778391111716"}, {"ref": "BomRef.6417637412689788.6127480579264394"}, {"ref": "BomRef.6452545806228636.12287746458786353"}, {"ref": "BomRef.6580570921014888.9951550796619147"}, {"ref": "BomRef.6669977398024305.4723217036713029"}, {"ref": "BomRef.6743767678528101.7269812227437155"}, {"ref": "BomRef.6788307381703613.05486168545949355"}, {"ref": "BomRef.6831432901355264.41338237399294275"}, {"ref": "BomRef.6918129463455259.9468169449604915"}, {"ref": "BomRef.6942021892584074.5748092195724882"}, {"ref": "BomRef.6992461754526389.7510895063046414"}, {"ref": "BomRef.7106727829954812.17197698957078567"}, {"ref": "BomRef.7113328605007135.9556352741617771"}, {"ref": "BomRef.7134151564880283.38609432472679805"}, {"ref": "BomRef.7232729525902583.686408138680244"}, {"ref": "BomRef.7322151312063863.15630250457850647"}, {"ref": "BomRef.7377623823272478.45407423468931296"}, {"ref": "BomRef.7428805630182203.4877805608901593"}, {"ref": "BomRef.7543066008924597.644470797767721"}, {"ref": "BomRef.7791144226107911.1059632306272088"}, {"ref": "BomRef.7829826871814832.7608884104862831"}, {"ref": "BomRef.813066367868474.8563078671542272"}, {"ref": "BomRef.8211668301153788.13416718098016134"}, {"ref": "BomRef.8366084590289321.1114078513054112"}, {"ref": "BomRef.8383120734283115.7280510717171598"}, {"ref": "BomRef.8416444172671227.926183573150287"}, {"ref": "BomRef.8469895377413493.4091653914070247"}, {"ref": "BomRef.8694090372348136.778617654467549"}, {"ref": "BomRef.8790773462058938.20104419892381864"}, {"ref": "BomRef.8841994252550259.6093844834991451"}, {"ref": "BomRef.8904358925853593.4697157957256769"}, {"ref": "BomRef.8982286851756128.6213442290605593"}, {"ref": "BomRef.9005669283075488.4531662567715601"}, {"ref": "BomRef.9030710234415519.3898658692188427"}, {"ref": "BomRef.906389014583216.0926475639659724"}, {"ref": "BomRef.9091347307262968.9298046928453801"}, {"ref": "BomRef.9310965691081283.6732072686612556"}, {"ref": "BomRef.9323938784552889.033040838742968814"}, {"ref": "BomRef.946084528250272.9720416722856347"}, {"ref": "BomRef.9500375501838764.26196138531617497"}, {"ref": "BomRef.9540461553556236.8523954278642786"}, {"ref": "BomRef.9555010294142502.7393913907566925"}, {"ref": "BomRef.9653513611439518.23564826610827172"}, {"ref": "BomRef.9736467397543925.4045819274572784"}, {"ref": "BomRef.9756996271792152.08987728010393159"}, {"ref": "BomRef.9762755608226122.338981861713919"}, {"ref": "BomRef.9881861706008136.6600129289201654"}, {"ref": "BomRef.9935845075961814.6691869783231301"}], "metadata": {"timestamp": "2026-06-23T06:20:40.444042+00:00"}, "serialNumber": "urn:uuid:1015bb18-fbf5-43dd-8213-1ed076ac1a4e", "version": 1, "$schema": "http://cyclonedx.org/schema/bom-1.4.schema.json", "bomFormat": "CycloneDX", "specVersion": "1.4"}
